__init__.py
django_help/__init__.py
django_help/admin.py
django_help/app_settings.py
django_help/apps.py
django_help/checks.py
django_help/choices.py
django_help/forms.py
django_help/models.py
django_help/tests.py
django_help/urls.py
django_help/views.py
django_help/migrations/0001_initial.py
django_help/migrations/__init__.py
django_help/templatetags/__init__.py
django_help/templatetags/django_help_tags.py
django_help/utils/__init__.py
django_help/utils/exporting.py
django_help/utils/importing.py
django_help/utils/queryset.py
django_help/utils/regex.py
django_help/utils/validation.py
django_help-2024.10.1.dist-info/LICENSE
django_help-2024.10.1.dist-info/METADATA
django_help-2024.10.1.dist-info/WHEEL
django_help-2024.10.1.dist-info/top_level.txt
django_help-2024.10.1.dist-info/RECORD
