Metadata-Version: 2.1
Name: django-help
Version: 2024.10.1
Summary: A Django Knowledgebase
Author-email: Jack Linke <jacklinke@gmail.com>
License: MIT
Project-URL: Homepage, https://github.com/OmenApps/django-help
Project-URL: Repository, https://github.com/OmenApps/django-help
Project-URL: Documentation, https://django-help.readthedocs.io
Project-URL: Changelog, https://github.com/OmenApps/django-help/releases
Classifier: Environment :: Web Environment
Classifier: Framework :: Django
Classifier: Framework :: Django :: 4.2
Classifier: Framework :: Django :: 5.0
Classifier: Framework :: Django :: 5.1
Classifier: Development Status :: 1 - Planning
Classifier: Intended Audience :: Developers
Classifier: License :: OSI Approved :: MIT License
Classifier: Operating System :: OS Independent
Classifier: Programming Language :: Python
Classifier: Programming Language :: Python :: 3
Classifier: Programming Language :: Python :: 3.10
Classifier: Programming Language :: Python :: 3.11
Classifier: Programming Language :: Python :: 3.12
Classifier: Programming Language :: Python :: 3.13
Classifier: Topic :: Internet :: WWW/HTTP
Classifier: Topic :: Internet :: WWW/HTTP :: Dynamic Content
Classifier: Topic :: Software Development
Classifier: Topic :: Software Development :: Libraries
Requires-Python: <4.0,>=3.10
License-File: LICENSE
Requires-Dist: django >=4.2
Requires-Dist: click >=8.1.7
Requires-Dist: django-markdownx >=4.0.7
Requires-Dist: django-translated-fields >=0.13.0
Requires-Dist: django-taggit >=6.1.0
Requires-Dist: python-frontmatter >=1.1.0
Requires-Dist: django-crispy-forms >=2.3
Requires-Dist: crispy-bootstrap5 >=2024.2
